kcell-0.1.0.dist-info/METADATA
kcell-0.1.0.dist-info/WHEEL
kcell/__init__.py
kcell/__init__.pyi
kcell/py.typed
kcell/kcell.abi3.so
kcell-0.1.0.dist-info/RECORD
