Metadata-Version: 2.4
Name: kcell
Version: 0.1.0
Requires-Dist: pytest ; extra == 'dev'
Provides-Extra: dev
Requires-Python: >=3.7
